MANIFEST.in
setup.py
cmsplugin_file/__init__.py
cmsplugin_file/cms_plugins.py
cmsplugin_file/models.py
cmsplugin_file.egg-info/PKG-INFO
cmsplugin_file.egg-info/SOURCES.txt
cmsplugin_file.egg-info/dependency_links.txt
cmsplugin_file.egg-info/not-zip-safe
cmsplugin_file.egg-info/top_level.txt
cmsplugin_file/migrations/0001_initial.py
cmsplugin_file/migrations/0002_freeze.py
cmsplugin_file/migrations/0003_publisher.py
cmsplugin_file/migrations/0004_table_rename.py
cmsplugin_file/migrations/0005_publisher2.py
cmsplugin_file/migrations/__init__.py
cmsplugin_file/templates/cms/plugins/file.html