Metadata-Version: 1.0
Name: cmsplugin-file
Version: 1.0.0
Summary: File plugin for django-cms, fixes issues with native file plugin with External Media Storage (e.g. S3)
Home-page: UNKNOWN
Author: Pratik Vyas
Author-email: pratik.vyas@changer.nl
License: UNKNOWN
Platform: UNKNOWN
